SimpleSinglyLinkedList/__init__.py
SimpleSinglyLinkedList/linked_list.py
SimpleSinglyLinkedList/node.py
tests/__init__.py
tests/test_linked_list.py
tests/test_node.py
SimpleSinglyLinkedList-1.0.0.dist-info/LICENSE
SimpleSinglyLinkedList-1.0.0.dist-info/METADATA
SimpleSinglyLinkedList-1.0.0.dist-info/WHEEL
SimpleSinglyLinkedList-1.0.0.dist-info/top_level.txt
SimpleSinglyLinkedList-1.0.0.dist-info/RECORD
