Metadata-Version: 2.1
Name: SimpleSinglyLinkedList
Version: 1.0.0
Summary: package for singly linked list manipulations
Home-page: https://github.com/Shahll/SimpleSinglyLinkedList
Author: Shahll
Author-email: shahll.git@gmail.com
Project-URL: Bug Tracker, https://github.com/Shahll/SimpleSinglyLinkedList/issues
Classifier: Programming Language :: Python :: 3
Classifier: License :: OSI Approved :: MIT License
Classifier: Operating System :: OS Independent
Requires-Python: >=3.6
License-File: LICENSE
